frostrose/__init__.py
frostrose/climate_normals.py
frostrose/code_tables.py
frostrose/elements.py
frostrose/frost_client.py
frostrose/locations.py
frostrose/observations.py
frostrose/sources.py
frostrose-0.1.1.dist-info/LICENSE
frostrose-0.1.1.dist-info/METADATA
frostrose-0.1.1.dist-info/WHEEL
frostrose-0.1.1.dist-info/RECORD
