Metadata-Version: 2.1
Name: frostrose
Version: 0.1.1
Summary: A Python library for accessing the Norwegian Meteorological Institute frost.met.no API
License: MIT
Author: Paul Skeie
Requires-Python: >=3.10,<4.0
Classifier: License :: OSI Approved :: MIT License
Classifier: Programming Language :: Python :: 3
Classifier: Programming Language :: Python :: 3.10
Classifier: Programming Language :: Python :: 3.11
Requires-Dist: requests (>=2.31.0,<3.0.0)
